LICENSE
MANIFEST.in
README.md
requirements.txt
setup.py
job_client_redis/__init__.py
job_client_redis/__meta__.py
job_client_redis/cell_display.py
job_client_redis/client.py
job_client_redis/store.py
job_client_redis.egg-info/PKG-INFO
job_client_redis.egg-info/SOURCES.txt
job_client_redis.egg-info/dependency_links.txt
job_client_redis.egg-info/not-zip-safe
job_client_redis.egg-info/requires.txt
job_client_redis.egg-info/top_level.txt