Metadata-Version: 1.1
Name: job-client-redis
Version: 0.1.1
Summary: redis client in for jupyter-observablehq-bridge
Home-page: https://github.com/jupyter-observablehq-bridge/job-client-py-redis
Author: jupyter-observablehq-bridge
Author-email: olivier.borderies@gmail.com
License: NO
Download-URL: https://github.com/jupyter-observablehq-bridge/job-client-py-redis/tarball/0.1.1
Keywords: jupyter,observablehq,redis,client
Platform: UNKNOWN
Classifier: Development Status :: 4 - Beta
Classifier: License :: OSI Approved :: MIT License
Classifier: Programming Language :: Python :: 3.6
Classifier: Programming Language :: Python :: 3.7
Classifier: Programming Language :: Python :: 3.8
